hypothesis_trio/__init__.py
hypothesis_trio/_version.py
hypothesis_trio/stateful.py
hypothesis_trio/_tests/__init__.py
hypothesis_trio/_tests/test_async_stateful.py
hypothesis_trio/_tests/test_stateful.py
hypothesis_trio/_tests/test_trio_asyncio.py
hypothesis_trio-0.6.0.dist-info/LICENSE
hypothesis_trio-0.6.0.dist-info/METADATA
hypothesis_trio-0.6.0.dist-info/WHEEL
hypothesis_trio-0.6.0.dist-info/top_level.txt
hypothesis_trio-0.6.0.dist-info/RECORD
