Metadata-Version: 2.1
Name: hypothesis-trio
Version: 0.6.0
Summary: Hypothesis plugin for trio
Home-page: https://github.com/python-trio/hypothesis-trio
Author: Emmanuel Leblond
Author-email: emmanuel.leblond@gmail.com
License: MPL 2.0
Keywords: async,hypothesis,testing,trio
Platform: UNKNOWN
Classifier: License :: OSI Approved :: Mozilla Public License 2.0 (MPL 2.0)
Classifier: Operating System :: POSIX :: Linux
Classifier: Operating System :: MacOS :: MacOS X
Classifier: Operating System :: Microsoft :: Windows
Classifier: Programming Language :: Python :: 3 :: Only
Classifier: Programming Language :: Python :: Implementation :: CPython
Classifier: Programming Language :: Python :: Implementation :: PyPy
Classifier: Topic :: System :: Networking
Classifier: Topic :: Software Development :: Testing
Classifier: Framework :: Hypothesis
Classifier: Framework :: Trio
Requires-Python: >=3.6
License-File: LICENSE
Requires-Dist: trio (>=0.11)
Requires-Dist: hypothesis (>=6.7.0)
